drawline/__init__.py
drawline/color_process.py
drawline/cv_utils.py
drawline/draw_process.py
drawline/utils.py
drawline-0.3.4.dist-info/METADATA
drawline-0.3.4.dist-info/WHEEL
drawline-0.3.4.dist-info/top_level.txt
drawline-0.3.4.dist-info/RECORD
