Metadata-Version: 2.1
Name: drawline
Version: 0.3.4
Summary: Clean draw of  rectangle and polygon contours
Home-page: https://github.com/bendangnuksung/drawline
Author: bendangnuksung
Author-email: bendangnuksungimsong@gmail.com
License: MIT License
Platform: UNKNOWN
Classifier: Programming Language :: Python :: 3
Classifier: Operating System :: OS Independent
Requires-Dist: opencv-python (>=4.4.0.40)
Requires-Dist: numpy (>=1.18.4)
Requires-Dist: matplotlib (>=3.3.0)
